python_template/__init__.py
python_template/app.py
andy_python_template-0.1.1.dist-info/METADATA
andy_python_template-0.1.1.dist-info/WHEEL
andy_python_template-0.1.1.dist-info/licenses/LICENSE
andy_python_template-0.1.1.dist-info/RECORD
