Metadata-Version: 2.4
Name: andy-python-template
Version: 0.1.1
Summary: ETL Pipeline Implementation. Extract, Transform, and Load data from both local and remote data sources.
Project-URL: Homepage, https://github.com/bellanov/etl-pipeline
Project-URL: Issues, https://github.com/bellanov/etl-pipeline/issues
Author-email: Bellanov Apilli <bellanovapilli@gmail.com>
License-File: LICENSE
Classifier: License :: OSI Approved :: MIT License
Classifier: Operating System :: OS Independent
Classifier: Programming Language :: Python :: 3
Requires-Python: >=3.8
